<?xml version="1.0" encoding="UTF-8"?>
<jcr:root xmlns:jcr="http://www.jcp.org/jcr/1.0" xmlns:sling="http://sling.apache.org/jcr/sling/1.0" xmlns:granite="http://www.adobe.com/jcr/granite/1.0"
          jcr:primaryType="nt:unstructured"
          jcr:title="SME - Benefits and USP Module dialog"
          sling:resourceType="cq/gui/components/authoring/dialog">
    <content
            jcr:primaryType="nt:unstructured"
            granite:class="benefits"
            sling:resourceType="granite/ui/components/coral/foundation/container">
        <items jcr:primaryType="nt:unstructured">
            <tabs
                    jcr:primaryType="nt:unstructured"
                    sling:resourceType="granite/ui/components/coral/foundation/tabs">
                <items jcr:primaryType="nt:unstructured">
                    <general
                            jcr:primaryType="nt:unstructured"
                            jcr:title="General"
                            sling:resourceType="granite/ui/components/coral/foundation/container">
                        <items jcr:primaryType="nt:unstructured">
                            <columns
                                    jcr:primaryType="nt:unstructured"
                                    sling:resourceType="granite/ui/components/coral/foundation/fixedcolumns">
                                <items jcr:primaryType="nt:unstructured">
                                    <column
                                            jcr:primaryType="nt:unstructured"
                                            sling:resourceType="granite/ui/components/coral/foundation/container">
                                        <items jcr:primaryType="nt:unstructured">
                                            <headline
                                                    jcr:primaryType="nt:unstructured"
                                                    fieldLabel="Headline"
                                                    name="./headline"
                                                    sling:resourceType="granite/ui/components/coral/foundation/form/textfield"/>
                                            <secondaryHeadline
                                                    jcr:primaryType="nt:unstructured"
                                                    fieldLabel="Secondary Headline"
                                                    name="./secondaryHeadline"
                                                    sling:resourceType="granite/ui/components/coral/foundation/form/textfield"/>
                                        </items>
                                    </column>
                                </items>
                            </columns>
                        </items>
                    </general>
                </items>
            </tabs>
        </items>
    </content>
</jcr:root>
